bulot/__about__.py
bulot/__init__.py
bulot/_py_version.py
bulot/_types.py
bulot/aliases.py
bulot/command.py
bulot/file_operations.py
bulot/logger.py
bulot/pipe.py
bulot/shell.py
bulot/utils.py
bulot/xargs.py
bulot-0.0.4.dist-info/METADATA
bulot-0.0.4.dist-info/WHEEL
bulot-0.0.4.dist-info/licenses/LICENSE
bulot-0.0.4.dist-info/RECORD
