Metadata-Version: 2.1
Name: bulot
Version: 0.0.4
Summary: Helper to run Bash commands with python
Project-URL: Documentation, https://github.com/yoann9344/bulot#readme
Project-URL: Issues, https://github.com/yoann9344/bulot/issues
Project-URL: Source, https://github.com/yoann9344/bulot
Author: Yoann
License-File: LICENSE
Classifier: Development Status :: 4 - Beta
Classifier: Programming Language :: Python
Classifier: Programming Language :: Python :: 3.7
Classifier: Programming Language :: Python :: 3.8
Classifier: Programming Language :: Python :: 3.9
Classifier: Programming Language :: Python :: 3.10
Classifier: Programming Language :: Python :: 3.11
Classifier: Programming Language :: Python :: Implementation :: CPython
Classifier: Programming Language :: Python :: Implementation :: PyPy
Requires-Python: >=3.7
Requires-Dist: rich
Provides-Extra: fixer
Requires-Dist: black; extra == 'fixer'
Provides-Extra: lint
Requires-Dist: flake8; extra == 'lint'
Provides-Extra: typecheck
Requires-Dist: mypy; extra == 'typecheck'
